odoo/addons/web_translate_dialog/README.rst
odoo/addons/web_translate_dialog/__init__.py
odoo/addons/web_translate_dialog/__manifest__.py
odoo/addons/web_translate_dialog/i18n/ar.po
odoo/addons/web_translate_dialog/i18n/ca.po
odoo/addons/web_translate_dialog/i18n/de.po
odoo/addons/web_translate_dialog/i18n/es.po
odoo/addons/web_translate_dialog/i18n/fi.po
odoo/addons/web_translate_dialog/i18n/fr.po
odoo/addons/web_translate_dialog/i18n/hr.po
odoo/addons/web_translate_dialog/i18n/it.po
odoo/addons/web_translate_dialog/i18n/nl.po
odoo/addons/web_translate_dialog/i18n/nl_NL.po
odoo/addons/web_translate_dialog/i18n/pt_BR.po
odoo/addons/web_translate_dialog/i18n/sl.po
odoo/addons/web_translate_dialog/i18n/tr.po
odoo/addons/web_translate_dialog/i18n/web_translate_dialog.pot
odoo/addons/web_translate_dialog/models/__init__.py
odoo/addons/web_translate_dialog/models/base.py
odoo/addons/web_translate_dialog/models/res_lang.py
odoo/addons/web_translate_dialog/readme/CONTRIBUTORS.rst
odoo/addons/web_translate_dialog/readme/DESCRIPTION.rst
odoo/addons/web_translate_dialog/readme/USAGE.rst
odoo/addons/web_translate_dialog/static/description/icon.png
odoo/addons/web_translate_dialog/static/description/index.html
odoo/addons/web_translate_dialog/static/src/css/base.css
odoo/addons/web_translate_dialog/static/src/js/web_translate_dialog.js
odoo/addons/web_translate_dialog/static/src/xml/base.xml
odoo/addons/web_translate_dialog/views/res_lang.xml
odoo/addons/web_translate_dialog/views/web_translate.xml
odoo12_addon_web_translate_dialog-12.0.1.2.2.dist-info/METADATA
odoo12_addon_web_translate_dialog-12.0.1.2.2.dist-info/WHEEL
odoo12_addon_web_translate_dialog-12.0.1.2.2.dist-info/top_level.txt
odoo12_addon_web_translate_dialog-12.0.1.2.2.dist-info/RECORD
